MANIFEST.in
README.rst
popit_api.py
setup.py
PopIt_Python.egg-info/PKG-INFO
PopIt_Python.egg-info/SOURCES.txt
PopIt_Python.egg-info/dependency_links.txt
PopIt_Python.egg-info/requires.txt
PopIt_Python.egg-info/top_level.txt