Metadata-Version: 1.0
Name: PopIt-Python
Version: 0.1.11
Summary: Python bindings to connect to the PopIt API
Home-page: https://github.com/mysociety/popit-python
Author: mySociety
Author-email: modules@mysociety.org
License: UNKNOWN
Platform: UNKNOWN
